eventsourcingdb/__init__.py
eventsourcingdb/bound.py
eventsourcingdb/client.py
eventsourcingdb/container.py
eventsourcingdb/is_event.py
eventsourcingdb/is_heartbeat.py
eventsourcingdb/is_stream_error.py
eventsourcingdb/is_valid_server_header.py
eventsourcingdb/pandas.py
eventsourcingdb/parse_raw_message.py
eventsourcingdb/py.typed
eventsourcingdb/errors/__init__.py
eventsourcingdb/errors/client_error.py
eventsourcingdb/errors/custom_error.py
eventsourcingdb/errors/internal_error.py
eventsourcingdb/errors/server_error.py
eventsourcingdb/errors/validation_error.py
eventsourcingdb/event/__init__.py
eventsourcingdb/event/event.py
eventsourcingdb/event/event_candidate.py
eventsourcingdb/http_client/__init__.py
eventsourcingdb/http_client/get_get_headers.py
eventsourcingdb/http_client/get_post_headers.py
eventsourcingdb/http_client/http_client.py
eventsourcingdb/http_client/response.py
eventsourcingdb/observe_events/__init__.py
eventsourcingdb/observe_events/if_event_is_missing_during_observe.py
eventsourcingdb/observe_events/observe_events_options.py
eventsourcingdb/observe_events/observe_from_latest_event.py
eventsourcingdb/read_event_types/__init__.py
eventsourcingdb/read_event_types/event_type.py
eventsourcingdb/read_event_types/is_event_type.py
eventsourcingdb/read_events/__init__.py
eventsourcingdb/read_events/if_event_is_missing_during_read.py
eventsourcingdb/read_events/order.py
eventsourcingdb/read_events/read_events_options.py
eventsourcingdb/read_events/read_from_latest_event.py
eventsourcingdb/read_subjects/__init__.py
eventsourcingdb/read_subjects/is_subject.py
eventsourcingdb/write_events/__init__.py
eventsourcingdb/write_events/preconditions.py
eventsourcingdb-1.9.0.dist-info/METADATA
eventsourcingdb-1.9.0.dist-info/WHEEL
eventsourcingdb-1.9.0.dist-info/licenses/LICENSE.md
eventsourcingdb-1.9.0.dist-info/RECORD
