Metadata-Version: 2.4
Name: eventsourcingdb
Version: 1.9.0
Summary: The official Python client SDK for EventSourcingDB.
Author-email: the native web GmbH <hello@thenativeweb.io>
License-Expression: MIT
License-File: LICENSE.md
Requires-Python: <3.15,>=3.11
Requires-Dist: aiohttp==3.13.2
Requires-Dist: cryptography==46.0.3
Requires-Dist: testcontainers==4.13.2
